race/__init__.py
race/entry.py
pytest_race-0.2.0.dist-info/AUTHORS
pytest_race-0.2.0.dist-info/LICENSE
pytest_race-0.2.0.dist-info/METADATA
pytest_race-0.2.0.dist-info/WHEEL
pytest_race-0.2.0.dist-info/entry_points.txt
pytest_race-0.2.0.dist-info/top_level.txt
pytest_race-0.2.0.dist-info/RECORD
